firebase_admin/__about__.py
firebase_admin/__init__.py
firebase_admin/_auth_client.py
firebase_admin/_auth_providers.py
firebase_admin/_auth_utils.py
firebase_admin/_gapic_utils.py
firebase_admin/_http_client.py
firebase_admin/_messaging_encoder.py
firebase_admin/_messaging_utils.py
firebase_admin/_retry.py
firebase_admin/_rfc3339.py
firebase_admin/_sseclient.py
firebase_admin/_token_gen.py
firebase_admin/_user_identifier.py
firebase_admin/_user_import.py
firebase_admin/_user_mgt.py
firebase_admin/_utils.py
firebase_admin/app_check.py
firebase_admin/auth.py
firebase_admin/credentials.py
firebase_admin/db.py
firebase_admin/exceptions.py
firebase_admin/firestore.py
firebase_admin/firestore_async.py
firebase_admin/functions.py
firebase_admin/instance_id.py
firebase_admin/messaging.py
firebase_admin/ml.py
firebase_admin/project_management.py
firebase_admin/remote_config.py
firebase_admin/storage.py
firebase_admin/tenant_mgt.py
firebase_admin-6.9.0.dist-info/LICENSE
firebase_admin-6.9.0.dist-info/METADATA
firebase_admin-6.9.0.dist-info/WHEEL
firebase_admin-6.9.0.dist-info/top_level.txt
firebase_admin-6.9.0.dist-info/RECORD
